{
  "version": "2.1.0",
  "flags": {},
  "shapes": [
    {
      "label": "7d",
      "points": [
        [
          1176.2224292755127,
          1843.6170196533203
        ],
        [
          1328.578119277954,
          1843.6170196533203
        ],
        [
          1328.578119277954,
          2171.8525314331055
        ],
        [
          1176.2224292755127,
          2171.8525314331055
        ]
      ],
      "group_id": null,
      "description": null,
      "difficult": false,
      "shape_type": "rectangle",
      "flags": {},
      "attributes": {}
    },
    {
      "label": "7d",
      "points": [
        [
          456.1711883544922,
          1139.6485328674316
        ],
        [
          602.7966976165771,
          1139.6485328674316
        ],
        [
          602.7966976165771,
          1459.706974029541
        ],
        [
          456.1711883544922,
          1459.706974029541
        ]
      ],
      "group_id": null,
      "description": null,
      "difficult": false,
      "shape_type": "rectangle",
      "flags": {},
      "attributes": {}
    },
    {
      "label": "9c",
      "points": [
        [
          1469.5764636993408,
          1965.8801078796387
        ],
        [
          1779.697437286377,
          1965.8801078796387
        ],
        [
          1779.697437286377,
          2189.769115447998
        ],
        [
          1469.5764636993408,
          2189.769115447998
        ]
      ],
      "group_id": null,
      "description": null,
      "difficult": false,
      "shape_type": "rectangle",
      "flags": {},
      "attributes": {}
    },
    {
      "label": "Qh",
      "points": [
        [
          1165.7731342315674,
          824.9203777313232
        ],
        [
          1466.6924381256104,
          824.9203777313232
        ],
        [
          1466.6924381256104,
          978.2766437530518
        ],
        [
          1165.7731342315674,
          978.2766437530518
        ]
      ],
      "group_id": null,
      "description": null,
      "difficult": false,
      "shape_type": "rectangle",
      "flags": {},
      "attributes": {}
    }
  ],
  "imagePath": "IMG_20231225_133425.jpg",
  "imageData": null,
  "imageHeight": 2200,
  "imageWidth": 2200
}